odoo10_addon_stock_scanner-10.0.1.1.2-nspkg.pth
odoo/addons/stock_scanner/README.rst
odoo/addons/stock_scanner/__init__.py
odoo/addons/stock_scanner/__manifest__.py
odoo/addons/stock_scanner/load_scenario.py
odoo/addons/stock_scanner/data/ir_cron.xml
odoo/addons/stock_scanner/data/stock_scanner.xml
odoo/addons/stock_scanner/data/scenarios/Login/Login.scenario
odoo/addons/stock_scanner/data/scenarios/Login/stock_scanner.scanner_scenario_login_step_done.py
odoo/addons/stock_scanner/data/scenarios/Login/stock_scanner.scanner_scenario_login_step_error.py
odoo/addons/stock_scanner/data/scenarios/Login/stock_scanner.scanner_scenario_login_step_login.py
odoo/addons/stock_scanner/data/scenarios/Login/stock_scanner.scanner_scenario_login_step_pwd.py
odoo/addons/stock_scanner/data/scenarios/Logout/Logout.scenario
odoo/addons/stock_scanner/data/scenarios/Logout/stock_scanner.scanner_scenario_logout_step_cancelled.py
odoo/addons/stock_scanner/data/scenarios/Logout/stock_scanner.scanner_scenario_logout_step_confirm.py
odoo/addons/stock_scanner/data/scenarios/Logout/stock_scanner.scanner_scenario_logout_step_confirmed.py
odoo/addons/stock_scanner/data/scenarios/Stock/Stock.scenario
odoo/addons/stock_scanner/demo/stock_scanner_demo.xml
odoo/addons/stock_scanner/demo/Tutorial/Tutorial.scenario
odoo/addons/stock_scanner/demo/Tutorial/Sentinel/Sentinel.scenario
odoo/addons/stock_scanner/demo/Tutorial/Sentinel/scanner_scenario_step_sentinel_going_back.py
odoo/addons/stock_scanner/demo/Tutorial/Sentinel/scanner_scenario_step_sentinel_introduction.py
odoo/addons/stock_scanner/demo/Tutorial/Sentinel/scanner_scenario_step_sentinel_list_scrolling.py
odoo/addons/stock_scanner/demo/Tutorial/Sentinel/scanner_scenario_step_sentinel_return_values.py
odoo/addons/stock_scanner/demo/Tutorial/Sentinel/scanner_scenario_step_sentinel_scrolling.py
odoo/addons/stock_scanner/demo/Tutorial/Step_types/Step_types.scenario
odoo10_addon_stock_scanner-10.0.1.1.2.dist-info/METADATA
odoo10_addon_stock_scanner-10.0.1.1.2.dist-info/WHEEL
odoo10_addon_stock_scanner-10.0.1.1.2.dist-info/namespace_packages.txt
odoo10_addon_stock_scanner-10.0.1.1.2.dist-info/top_level.txt
odoo10_addon_stock_scanner-10.0.1.1.2.dist-info/RECORD
